<package>
  <description brief="summit_controller">

     summit_controller

  </description>
  <author>Robotnik</author>
  <license>BSD</license>
  <review status="unreviewed" notes=""/>
  <url>http://ros.org/wiki/summit_controller</url>
  <depend package="pr2_controller_interface"/>
  <depend package="pr2_mechanism_model"/>
  <depend package="pluginlib"/>
  <depend package="roscpp"/>
  <depend package="tf"/>
  <depend package="sensor_msgs"/>
  <depend package="nav_msgs"/>
  <depend package="robotnik_msgs"/>

  <export>
     <pr2_controller_interface plugin="${prefix}/controller_plugins.xml" />
  </export>

</package>


